mcmng/__init__.py
mcmng/__main__.py
mcmng/backup.py
mcmng-0.2.0.dist-info/LICENSE
mcmng-0.2.0.dist-info/WHEEL
mcmng-0.2.0.dist-info/METADATA
mcmng-0.2.0.dist-info/RECORD
